mcp_timeserver/__init__.py
mcp_timeserver/server.py
mcp_timeserver-0.1.0.dist-info/METADATA
mcp_timeserver-0.1.0.dist-info/WHEEL
mcp_timeserver-0.1.0.dist-info/entry_points.txt
mcp_timeserver-0.1.0.dist-info/licenses/LICENSE
mcp_timeserver-0.1.0.dist-info/RECORD
